blackini/__init__.py
blackini/__main__.py
blackini-0.1.6.dist-info/entry_points.txt
blackini-0.1.6.dist-info/WHEEL
blackini-0.1.6.dist-info/METADATA
blackini-0.1.6.dist-info/RECORD
