Metadata-Version: 2.1
Name: blackini
Version: 0.1.6
Summary: 
Author: Pablo Woolvett
Author-email: pablowoolvett@gmail.com
Requires-Python: >=3.6,<4.0
Classifier: Programming Language :: Python :: 3
Classifier: Programming Language :: Python :: 3.6
Classifier: Programming Language :: Python :: 3.7
Requires-Dist: black (>=19.3b0,<20.0)
